microx_core.cpython-39-x86_64-linux-gnu.so
microx/__init__.py
microx-1.4.1.dist-info/LICENSE
microx-1.4.1.dist-info/METADATA
microx-1.4.1.dist-info/top_level.txt
microx-1.4.1.dist-info/WHEEL
microx-1.4.1.dist-info/RECORD
