Metadata-Version: 2.1
Name: microx
Version: 1.4.1
Summary: x86 and x86_64 micro-executor.
Home-page: https://github.com/trailofbits/microx
Author: Peter Goodman
Author-email: peter@trailofbits.com
License: Apache-2.0
Platform: UNKNOWN
Requires-Python: >=3.7
